awsglue_rclone/__init__.py
awsglue_rclone/config.py
awsglue_rclone/obscure.py
awsglue_rclone/utils.py
awsglue_rclone-0.0.2.dist-info/LICENSE
awsglue_rclone-0.0.2.dist-info/METADATA
awsglue_rclone-0.0.2.dist-info/WHEEL
awsglue_rclone-0.0.2.dist-info/top_level.txt
awsglue_rclone-0.0.2.dist-info/RECORD
