Metadata-Version: 2.1
Name: awsglue-rclone
Version: 0.0.2
Summary: RClone Wrapper for AWS Glue Python Shell
Home-page: UNKNOWN
Author: Wang Zhiwei
Author-email: noparking188@gmail.com
License: UNKNOWN
Keywords: awsglue rclone
Platform: UNKNOWN
Classifier: Programming Language :: Python :: 3
Classifier: License :: OSI Approved :: GNU General Public License v3 or later (GPLv3+)
Requires-Python: >=3.7
License-File: LICENSE
Requires-Dist: urllib3 ==1.26.18
Requires-Dist: requests <3,>=2.27.1
Requires-Dist: boto3 >=1.22.5
Requires-Dist: redo ==2.0.4
Requires-Dist: cryptography ~=42.0.2
